MANIFEST.in
README.md
requirements.txt
setup.cfg
setup.py
wolframalpha.py
wolframalpha_cli.egg-info/PKG-INFO
wolframalpha_cli.egg-info/SOURCES.txt
wolframalpha_cli.egg-info/dependency_links.txt
wolframalpha_cli.egg-info/entry_points.txt
wolframalpha_cli.egg-info/requires.txt
wolframalpha_cli.egg-info/top_level.txt