Metadata-Version: 2.1
Name: wolframalpha-cli
Version: 1.1.0
Summary: Command Line Interface to run queries on WolframAlpha
Home-page: https://github.com/fcrespo82/wolframalpha-cli
Author: Fernando Xavier de Freitas Crespo
Author-email: fernando82@gmail.com
License: MIT
Keywords: wolframalpha cli python utility
Platform: UNKNOWN
Classifier: Environment :: Console
Classifier: Topic :: Utilities
Classifier: License :: OSI Approved :: MIT License
